pmpsdb_client/__init__.py
pmpsdb_client/__main__.py
pmpsdb_client/_version.py
pmpsdb_client/beam_class.py
pmpsdb_client/data_types.py
pmpsdb_client/device_map.ui
pmpsdb_client/export_data.py
pmpsdb_client/ftp_data.py
pmpsdb_client/gui.py
pmpsdb_client/ioc_data.py
pmpsdb_client/plc_data.py
pmpsdb_client/pmpsdb_kfe.yml
pmpsdb_client/pmpsdb_lfe.yml
pmpsdb_client/pmpsdb_rix.yml
pmpsdb_client/pmpsdb_tmo.yml
pmpsdb_client/pmpsdb_tst.yml
pmpsdb_client/pmpsdb_txi_hard.yml
pmpsdb_client/pmpsdb_txi_soft.yml
pmpsdb_client/pmpsdb_xpp.yml
pmpsdb_client/ssh_data.py
pmpsdb_client/tables.ui
pmpsdb_client/version.py
pmpsdb_client/cli/__init__.py
pmpsdb_client/cli/epics_tools.py
pmpsdb_client/cli/parser.py
pmpsdb_client/cli/run_gui.py
pmpsdb_client/cli/transfer_tools.py
pmpsdb_client/tests/test_cli.py
pmpsdb_client/tests/test_gui.py
pmpsdb_client-1.3.0.dist-info/licenses/LICENSE.md
pmpsdb_client-1.3.0.dist-info/METADATA
pmpsdb_client-1.3.0.dist-info/WHEEL
pmpsdb_client-1.3.0.dist-info/entry_points.txt
pmpsdb_client-1.3.0.dist-info/top_level.txt
pmpsdb_client-1.3.0.dist-info/RECORD
