Metadata-Version: 2.4
Name: pmpsdb_client
Version: 1.3.0
Summary: Client application for interfacing with the PMPS database and the deployed PLC files.
Author: SLAC National Accelerator Laboratory
License: Copyright (c) 2022, The Board of Trustees of the Leland Stanford Junior
Keywords: pmps,pmpsdb,lcls
Classifier: Development Status :: 4 - Beta
Classifier: Natural Language :: English
Classifier: Programming Language :: Python :: 3
Requires-Python: >=3.9
License-File: LICENSE.md
Requires-Dist: fabric
Requires-Dist: ophyd
Requires-Dist: pcdscalc
Requires-Dist: pcdsutils
Requires-Dist: prettytable
Requires-Dist: qtpy
Provides-Extra: test
Requires-Dist: PyQt5; extra == "test"
Requires-Dist: pytest; extra == "test"
Requires-Dist: setuptools-scm; extra == "test"
Dynamic: license-file
